{"version":1,"resource":"vscode-remote://970-cs-98853294-8db9-43eb-b27b-8f2fb7f5c5ce.cs-asia-southeast1-bool.cloudshell.dev/home/youwantsomethings/real_dataflow_etl.py","entries":[{"id":"oIMc.py","source":"textFileCreate.source","timestamp":1728385698213},{"id":"kyqr.py","timestamp":1728385926366},{"id":"Rm8h.py","timestamp":1728386030678},{"id":"1f6T.py","timestamp":1728389538569},{"id":"d84j.py","timestamp":1728389680901},{"id":"1gxb.py","timestamp":1728390819830},{"id":"ORbG.py","timestamp":1728390883883},{"id":"SLrr.py","timestamp":1728391022928},{"id":"IiDB.py","timestamp":1728391141021},{"id":"MT95.py","timestamp":1728391259817},{"id":"BTPI.py","timestamp":1728391280299},{"id":"ghsV.py","timestamp":1728391349192},{"id":"q8kr.py","timestamp":1728391364536},{"id":"QpDi.py","timestamp":1728391446898},{"id":"iiVo.py","source":"undoRedo.source","timestamp":1728391448899},{"id":"V7pU.py","timestamp":1728391452055},{"id":"ZB5s.py","source":"undoRedo.source","timestamp":1728391470654},{"id":"XOnD.py","timestamp":1728391481870},{"id":"zdRk.py","timestamp":1728391538292},{"id":"DCQT.py","timestamp":1728391646894},{"id":"kMxU.py","timestamp":1728391660043},{"id":"wDxy.py","timestamp":1728391840242}]}